command2img/__init__.py
command2img/__main__.py
command2img/txt2img/__init__.py
command2img/txt2img/fonts/meslo.ttf
command2img-0.3.1.data/scripts/command2img
command2img-0.3.1.dist-info/LICENSE
command2img-0.3.1.dist-info/METADATA
command2img-0.3.1.dist-info/WHEEL
command2img-0.3.1.dist-info/top_level.txt
command2img-0.3.1.dist-info/RECORD
