Metadata-Version: 2.1
Name: command2img
Version: 0.3.1
Summary: This is an simple program to convert a command line to image.
Home-page: https://github.com/emanuel-alves/command2img
Author: Emanuel Alves
Author-email: emanuel.alves@unifei.edu.br
License: MIT
Classifier: Intended Audience :: End Users/Desktop
Classifier: License :: OSI Approved :: MIT License
Classifier: Programming Language :: Python
Classifier: Programming Language :: Python :: 3
Classifier: Programming Language :: Python :: 3 :: Only
Classifier: Topic :: Utilities
License-File: LICENSE
Requires-Dist: Pillow ==9.5.0
